<Properties StartupConfiguration="{FC33DA20-A9C5-4E63-A475-FE92BF2DB77E}|Default">
  <MonoDevelop.Ide.ItemProperties.Shopping.Client PreferredExecutionTarget="/Applications/Google Chrome.app" />
  <MonoDevelop.Ide.Workbench ActiveDocument="../../../../../../Applications/Visual Studio.app/Contents/Resources/lib/monodevelop/AddIns/docker/MonoDevelop.Docker/MSBuild/Sdks/Microsoft.Docker.Sdk/build/Microsoft.VisualStudio.Docker.Compose.targets">
    <Files>
      <File FileName="Shopping.Client/Controllers/HomeController.cs" Line="27" Column="38" />
      <File FileName="../../../../../../Applications/Visual Studio.app/Contents/Resources/lib/monodevelop/AddIns/docker/MonoDevelop.Docker/MSbuild/Sdks/Microsoft.Docker.Sdk/build/Microsoft.VisualStudio.Docker.Compose.targets" Line="394" Column="5" />
    </Files>
    <Pads>
      <Pad Id="ProjectPad">
        <State name="__root__">
          <Node name="Shopping" expanded="True" selected="True" />
        </State>
      </Pad>
    </Pads>
  </MonoDevelop.Ide.Workbench>
  <MonoDevelop.Ide.DebuggingService.PinnedWatches />
  <MonoDevelop.Ide.Workspace ActiveConfiguration="Debug" />
  <MonoDevelop.Ide.ItemProperties.docker-compose PreferredExecutionTarget="MonoDevelop.Default" />
  <MonoDevelop.Ide.DebuggingService.Breakpoints>
    <BreakpointStore />
  </MonoDevelop.Ide.DebuggingService.Breakpoints>
  <MultiItemStartupConfigurations />
</Properties>